pytest_cldf/__init__.py
pytest_cldf/plugin.py
pytest_cldf-0.3.0.dist-info/LICENSE
pytest_cldf-0.3.0.dist-info/METADATA
pytest_cldf-0.3.0.dist-info/WHEEL
pytest_cldf-0.3.0.dist-info/entry_points.txt
pytest_cldf-0.3.0.dist-info/top_level.txt
pytest_cldf-0.3.0.dist-info/RECORD
