Metadata-Version: 2.1
Name: pytest-cldf
Version: 0.3.0
Summary: Easy quality control for CLDF datasets using pytest
Home-page: https://github.com/cldf/pytest-cldf/
License: UNKNOWN
Platform: UNKNOWN
Classifier: Framework :: Pytest
Requires-Dist: attrs (>=18.2)
Requires-Dist: pycldf (>=1.6.1)
Requires-Dist: pytest (>=3.6)
